yspdx/__init__.py
yspdx/cli.py
yspdx/models.py
yspdx/processor.py
yspdx/processors/__init__.py
yspdx/processors/binary_processor.py
yspdx/processors/full_processor.py
yspdx/processors/minimal_processor.py
yspdx-0.1.4.dist-info/METADATA
yspdx-0.1.4.dist-info/WHEEL
yspdx-0.1.4.dist-info/entry_points.txt
yspdx-0.1.4.dist-info/licenses/LICENSE
yspdx-0.1.4.dist-info/RECORD
