Metadata-Version: 2.4
Name: yspdx
Version: 0.1.4
Summary: SPDX file processor for master yocto system information from create-spdx.bbclass
Author-email: Dinesh Ravi <dineshr93@gmail.com>
License-Expression: GPL-3.0-or-later
License-File: LICENSE
Requires-Python: >=3.10
Requires-Dist: zstandard>=0.22.0
